odoo/addons/product_tax_multicompany_default/README.rst
odoo/addons/product_tax_multicompany_default/__init__.py
odoo/addons/product_tax_multicompany_default/__manifest__.py
odoo/addons/product_tax_multicompany_default/i18n/de.po
odoo/addons/product_tax_multicompany_default/i18n/es.po
odoo/addons/product_tax_multicompany_default/i18n/fr.po
odoo/addons/product_tax_multicompany_default/i18n/it.po
odoo/addons/product_tax_multicompany_default/i18n/product_tax_multicompany_default.pot
odoo/addons/product_tax_multicompany_default/models/__init__.py
odoo/addons/product_tax_multicompany_default/models/product.py
odoo/addons/product_tax_multicompany_default/readme/CONFIGURE.rst
odoo/addons/product_tax_multicompany_default/readme/CONTRIBUTORS.rst
odoo/addons/product_tax_multicompany_default/readme/DESCRIPTION.rst
odoo/addons/product_tax_multicompany_default/readme/USAGE.rst
odoo/addons/product_tax_multicompany_default/static/description/icon.png
odoo/addons/product_tax_multicompany_default/static/description/index.html
odoo/addons/product_tax_multicompany_default/tests/__init__.py
odoo/addons/product_tax_multicompany_default/tests/test_product_tax_multicompany.py
odoo/addons/product_tax_multicompany_default/views/product_template_view.xml
odoo13_addon_product_tax_multicompany_default-13.0.1.0.1.dev6.dist-info/METADATA
odoo13_addon_product_tax_multicompany_default-13.0.1.0.1.dev6.dist-info/WHEEL
odoo13_addon_product_tax_multicompany_default-13.0.1.0.1.dev6.dist-info/top_level.txt
odoo13_addon_product_tax_multicompany_default-13.0.1.0.1.dev6.dist-info/RECORD
